CRYSTALClear/__init__.py
CRYSTALClear/adsorb.py
CRYSTALClear/calculate.py
CRYSTALClear/convert.py
CRYSTALClear/crystal_io.py
CRYSTALClear/execute.py
CRYSTALClear/geometry.py
CRYSTALClear/plot.py
CRYSTALClear/thermodynamics.py
CRYSTALClear/unit_test.py
CRYSTALClear/units.py
CRYSTALClear/utils.py
CRYSTALClear/base/__init__.py
CRYSTALClear/base/basisset.py
CRYSTALClear/base/crysd12.py
CRYSTALClear/base/crysout.py
CRYSTALClear/base/inputbase.py
CRYSTALClear/base/plotbase.py
CRYSTALClear/base/propout.py
CRYSTALClear-2023.7.24.dist-info/LICENSE.txt
CRYSTALClear-2023.7.24.dist-info/METADATA
CRYSTALClear-2023.7.24.dist-info/WHEEL
CRYSTALClear-2023.7.24.dist-info/top_level.txt
CRYSTALClear-2023.7.24.dist-info/RECORD
