Metadata-Version: 2.1
Name: CRYSTALClear
Version: 2023.7.24
Summary: Python framework for the CRYSTAL code.
Home-page: https://github.com/crystaldevs/CRYSTALClear
Author-email: crystalunito@gmail.com
Project-URL: Bug Tracker, https://github.com/crystaldevs/CRYSTALClear/issues
Classifier: Programming Language :: Python :: 3
Classifier: License :: OSI Approved :: MIT License
Classifier: Operating System :: OS Independent
License-File: LICENSE.txt
Requires-Dist: pymatgen
Requires-Dist: mendeleev
Requires-Dist: ase
